{
    "data": [
        {
            "assets": {
                "logo": "https://razzo-bucket.s3.amazonaws.com/public/business/609ee7c9daf43e472de400e4/1621031891179",
                "cover": "https://razzo-bucket.s3.sa-east-1.amazonaws.com/public/business/609ee7c9daf43e472de400e4/1621031902168"
            },
            "address": {
                "zipcode": "85867320",
                "street_name": "Capanema",
                "street_number": "4",
                "neighborhood": "Jardim Itaipu",
                "city": "Foz do Iguaçu",
                "state": "PR"
            },
            "deleted": false,
            "activated": true,
            "_id": "609ee7c9daf43e472de400e4",
            "name": "Razzo Pizza",
            "phone": "4599999999",
            "email": "razzopizza@gmail.com",
            "description": "Pizzaria Razzo",
            "createdAt": "2021-05-14T21:12:41.027Z",
            "updatedAt": "2021-05-14T22:38:22.665Z",
            "__v": 0
        },
        {
            "assets": {
                "cover": "https://razzo-bucket.s3.sa-east-1.amazonaws.com/public/business/609efc6aa16e1fb123f9574c/1621032056939",
                "logo": "https://razzo-bucket.s3.sa-east-1.amazonaws.com/public/business/609efc6aa16e1fb123f9574c/1621032071222"
            },
            "address": {
                "zipcode": "85867320",
                "street_name": "Capanema",
                "street_number": "4",
                "neighborhood": "Porto Belo",
                "city": "Foz do Iguaçu",
                "state": "PR"
            },
            "deleted": false,
            "activated": true,
            "_id": "609efc6aa16e1fb123f9574c",
            "name": "Razzo Hamburguer",
            "phone": "4599999999",
            "email": "razzopizza@gmail.com",
            "description": "Pizzaria Hamburguer",
            "createdAt": "2021-05-14T22:40:42.740Z",
            "updatedAt": "2021-05-14T22:41:11.566Z",
            "__v": 0
        },
        {
            "assets": {
                "logo": "https://razzo-bucket.s3.sa-east-1.amazonaws.com/public/business/609efc9aa16e1fb123f9574d/1621032101357",
                "cover": "https://razzo-bucket.s3.sa-east-1.amazonaws.com/public/business/609efc9aa16e1fb123f9574d/1621032111985"
            },
            "address": {
                "zipcode": "85867320",
                "street_name": "Capanema",
                "street_number": "4",
                "neighborhood": "Centro",
                "city": "Foz do Iguaçu",
                "state": "PR"
            },
            "deleted": false,
            "activated": true,
            "_id": "609efc9aa16e1fb123f9574d",
            "name": "Razzo Sushi",
            "phone": "4599999999",
            "email": "razzopizza@gmail.com",
            "description": "Pizzaria Sushi",
            "createdAt": "2021-05-14T22:41:30.046Z",
            "updatedAt": "2021-05-14T22:41:52.379Z",
            "__v": 0
        }
    ],
    "total": 3,
    "offset": 0,
    "limit": 3,
    "totalPages": 1,
    "page": 1,
    "pagingCounter": 1,
    "hasPrevPage": false,
    "hasNextPage": false,
    "prevPage": null,
    "nextPage": null
}